ordbok/__init__.py
ordbok/ordbok.py
ordbok/reader/__init__.py
ordbok/reader/demangle_dsl.py
ordbok/reader/dsl.py
ordbok/reader/test_dsl.py
ordbok/reader/flawless_dsl/__init__.py
ordbok/reader/flawless_dsl/layer.py
ordbok/reader/flawless_dsl/main.py
ordbok/reader/flawless_dsl/tag.py
ordbok/reader/flawless_dsl/tests.py
ordbok/static/css/aulismedia.css
ordbok/static/css/cambridge-style.css
ordbok/static/css/deepl.css
ordbok/static/css/glosbe-style.css
ordbok/static/css/iframe.css
ordbok/static/css/lexin-style.css
ordbok/static/css/naob-style.css
ordbok/static/css/ordbok-inflect.css
ordbok/static/css/ordbok-word.css
ordbok/static/css/ordbokene-word.css
ordbok/static/css/trex.css
ordbok/static/css/wiktionary-style.css
ordbok/static/html/aulismedia-norsk.html
ordbok/static/html/iframe-e.html
ordbok/static/html/iframe-fourth.html
ordbok/static/html/iframe-h.html
ordbok/static/html/iframe-mix.html
ordbok/static/html/iframe-nor.html
ordbok/static/html/iframe-q.html
ordbok/static/html/iframe-r.html
ordbok/static/html/iframe-third.html
ordbok/static/html/iframe-w.html
ordbok/static/html/index.html
ordbok/static/js/aulismedia.js
srst_ordbok-0.1.3.dist-info/METADATA
srst_ordbok-0.1.3.dist-info/WHEEL
srst_ordbok-0.1.3.dist-info/entry_points.txt
srst_ordbok-0.1.3.dist-info/top_level.txt
srst_ordbok-0.1.3.dist-info/RECORD
